pydk/_GIF.py
pydk/__init__.py
pydk/_class_attributes.py
pydk/_create_empty_dict.py
pydk/_current_time.py
pydk/_dynamical_import_of_function_from_string.py
pydk/_filter_overlapping.py
pydk/_find_overlapping.py
pydk/_flexible_multilevel_mkdir.py
pydk/_get_parent_directory.py
pydk/_load_pickled.py
pydk/_min_max_normalize.py
pydk/_mk_GCP_command.py
pydk/_rounding.py
pydk/_smooth_1d_array.py
pydk/_to_list.py
pydk/_update_python_class_attr.py
pydk/_conda_package_installer/_conda_package_installer.py
pydk/_conda_package_installer/_supporting_functions.py
pydk-0.0.54.dist-info/LICENSE
pydk-0.0.54.dist-info/METADATA
pydk-0.0.54.dist-info/WHEEL
pydk-0.0.54.dist-info/top_level.txt
pydk-0.0.54.dist-info/RECORD
